simlin/__init__.py
simlin/image_resize.py
simlin-0.0.6.data/scripts/simlin
simlin-0.0.6.dist-info/LICENSE
simlin-0.0.6.dist-info/METADATA
simlin-0.0.6.dist-info/WHEEL
simlin-0.0.6.dist-info/top_level.txt
simlin-0.0.6.dist-info/RECORD
