Metadata-Version: 2.1
Name: simlin
Version: 0.0.6
Summary: Simple Image Manipulator for Linux
Home-page: https://www.linuxnorth.org/simlin/
Download-URL: https://github.com/alaudet/simlin/releases
Author: Al Audet
Author-email: alaudet@linuxnorth.org
License: MIT License
Classifier: Development Status :: 4 - Beta
Classifier: Environment :: Console
Classifier: Intended Audience :: End Users/Desktop
Classifier: Natural Language :: English
Classifier: Operating System :: POSIX :: Linux
Classifier: Programming Language :: Python :: 3
Classifier: Topic :: Multimedia :: Graphics :: Graphics Conversion
Classifier: License :: OSI Approved :: MIT License
License-File: LICENSE
Requires-Dist: pillow
